endorphin/__init__.py
endorphin/cli.py
endorphin/endorphin.py
endorphin-0.1.2.dist-info/AUTHORS.rst
endorphin-0.1.2.dist-info/LICENSE
endorphin-0.1.2.dist-info/METADATA
endorphin-0.1.2.dist-info/WHEEL
endorphin-0.1.2.dist-info/entry_points.txt
endorphin-0.1.2.dist-info/top_level.txt
endorphin-0.1.2.dist-info/RECORD
