Metadata-Version: 2.1
Name: endorphin
Version: 0.1.2
Summary: A C++ Project boilerplate
Home-page: https://github.com/xq5he/endorphin
Author: Xinquan She
Author-email: shexinquan@gmail.com
License: MIT license
Keywords: endorphin
Platform: UNKNOWN
Classifier: Development Status :: 2 - Pre-Alpha
Classifier: Intended Audience :: Developers
Classifier: License :: OSI Approved :: MIT License
Classifier: Natural Language :: English
Classifier: Programming Language :: Python :: 3
Classifier: Programming Language :: Python :: 3.4
Classifier: Programming Language :: Python :: 3.5
Classifier: Programming Language :: Python :: 3.6
Classifier: Programming Language :: Python :: 3.7
Requires-Dist: Click (>=6.0)
